pymdgen/__init__.py
pymdgen/cli.py
pymdgen/md.py
pymdgen/test_getargspec.py
pymdgen/test_module.py
pymdgen-1.1.0.dist-info/METADATA
pymdgen-1.1.0.dist-info/WHEEL
pymdgen-1.1.0.dist-info/entry_points.txt
pymdgen-1.1.0.dist-info/licenses/LICENSE
pymdgen-1.1.0.dist-info/RECORD
